owl_crypto_py/__init__.py
owl_crypto_py/_messagesGenerator.py
owl_crypto_py/extended_curves.py
owl_crypto_py/messages.py
owl_crypto_py/owl_client.py
owl_crypto_py/owl_common.py
owl_crypto_py/owl_server.py
owl_crypto_py-1.0.12.dist-info/licenses/LICENSE.md
owl_crypto_py-1.0.12.dist-info/METADATA
owl_crypto_py-1.0.12.dist-info/WHEEL
owl_crypto_py-1.0.12.dist-info/top_level.txt
owl_crypto_py-1.0.12.dist-info/RECORD
