Metadata-Version: 2.4
Name: owl-crypto-py
Version: 1.0.12
Summary: Python implementation of the OWL aPAKE protocol
Author-email: Nicolò Marotta <nick007sbt@gmail.com>
License: MIT
Keywords: cryptography,pake,apake,authentication,owl,password
Classifier: Development Status :: 3 - Alpha
Classifier: Intended Audience :: Developers
Classifier: Topic :: Security :: Cryptography
Classifier: Programming Language :: Python :: 3
Classifier: Programming Language :: Python :: 3.10
Classifier: Programming Language :: Python :: 3.11
Classifier: Programming Language :: Python :: 3.12
Classifier: License :: OSI Approved :: MIT License
Classifier: Operating System :: OS Independent
Requires-Python: >=3.10
License-File: LICENSE.md
Requires-Dist: cryptography>=42.0.0
Dynamic: license-file
